egamma_tnp/__init__.py
egamma_tnp/_base_ntuplizer.py
egamma_tnp/_base_tagnprobe.py
egamma_tnp/_version.py
egamma_tnp/nanoaod_efficiency.py
egamma_tnp/nanoaod_sas_ntuples.py
egamma_tnp/ntuple_efficiency.py
egamma_tnp/plot.py
egamma_tnp/triggers.py
egamma_tnp/version.pyi
egamma_tnp/config/__init__.py
egamma_tnp/config/binning_manager.py
egamma_tnp/config/default_binning.json
egamma_tnp/scripts/__init__.py
egamma_tnp/scripts/dataset_query.py
egamma_tnp/scripts/fetch_datasets.py
egamma_tnp/scripts/get_unprocessed_partitions.py
egamma_tnp/scripts/merge_parquet.py
egamma_tnp/scripts/prepare_histograms.py
egamma_tnp/scripts/run_analysis.py
egamma_tnp/scripts/run_fitter.py
egamma_tnp/utils/__init__.py
egamma_tnp/utils/dataset.py
egamma_tnp/utils/default_runner_settings.json
egamma_tnp/utils/fitter_models.py
egamma_tnp/utils/fitter_utils.py
egamma_tnp/utils/histogramming.py
egamma_tnp/utils/logger_utils.py
egamma_tnp/utils/misc.py
egamma_tnp/utils/pileup.py
egamma_tnp/utils/rucio_utils.py
egamma_tnp/utils/runner_utils.py
egamma_tnp-0.6.0.dist-info/METADATA
egamma_tnp-0.6.0.dist-info/WHEEL
egamma_tnp-0.6.0.dist-info/entry_points.txt
egamma_tnp-0.6.0.dist-info/licenses/LICENSE
egamma_tnp-0.6.0.dist-info/RECORD
